express_relay_test/__init__.py
express_relay_test/client.py
express_relay_test/searcher/examples/simple_searcher.py
express_relay_test/types.py
express_relay_test-0.2.0.dist-info/METADATA
express_relay_test-0.2.0.dist-info/WHEEL
express_relay_test-0.2.0.dist-info/RECORD
