Metadata-Version: 2.1
Name: express-relay-test
Version: 0.2.0
Summary: Utilities for searchers and protocols to interact with the Express Relay protocol.
License: Proprietary
Author: dourolabs
Requires-Python: >=3.11,<4.0
Classifier: License :: Other/Proprietary License
Classifier: Programming Language :: Python :: 3
Classifier: Programming Language :: Python :: 3.11
Classifier: Programming Language :: Python :: 3.12
Requires-Dist: argparse (>=1.4.0,<2.0.0)
Requires-Dist: asyncio (>=3.4.3,<4.0.0)
Requires-Dist: eth_abi (>=4.2.1,<5.0.0)
Requires-Dist: eth_account (>=0.10.0,<0.11.0)
Requires-Dist: httpx (>=0.23.3,<0.24.0)
Requires-Dist: pydantic (>=2.6.3,<3.0.0)
Requires-Dist: web3 (>=6.15.1,<7.0.0)
Requires-Dist: websockets (>=11.0.3,<12.0.0)
